vcd/__init__.py
vcd/_version.py
vcd/core.py
vcd/draw.py
vcd/poly2d.py
vcd/sanity.py
vcd/schema.py
vcd/scl.py
vcd/types.py
vcd/utils.py
vcd-6.0.3.dist-info/LICENSE
vcd-6.0.3.dist-info/METADATA
vcd-6.0.3.dist-info/WHEEL
vcd-6.0.3.dist-info/top_level.txt
vcd-6.0.3.dist-info/RECORD
