Metadata-Version: 2.1
Name: vcd
Version: 6.0.3
Summary: Video Content Description (VCD) library
Author-email: Marcos Nieto <mnieto@vicomtech.org>, Juan Diego Ortega <jdortega@vicomtech.org>, Jon Goenetxea <jongoenetxea@vicomtech.org>
License: Copyright (c) 2023 Vicomtech
Project-URL: Homepage, https://vcd.vicomtech.org
Project-URL: Documentation, https://vicomtech.gitlab.io/v4/libraries/vcd/vcd-python/latest/vcd/
Project-URL: Changelog, https://vicomtech.gitlab.io/v4/libraries/vcd/vcd-python/latest/vcd/index.html#changelog
Classifier: Programming Language :: Python
Classifier: Programming Language :: Python :: 3
Classifier: Programming Language :: Python :: 3.8
Classifier: Programming Language :: Python :: 3.9
Classifier: Programming Language :: Python :: 3.10
Classifier: Programming Language :: Python :: 3.11
Classifier: Programming Language :: Python :: 3.12
Classifier: License :: OSI Approved :: MIT License
Classifier: Operating System :: OS Independent
Classifier: Topic :: Scientific/Engineering :: Artificial Intelligence
Requires-Python: >=3.8
License-File: LICENSE
Requires-Dist: jsonschema >=3.2
Requires-Dist: protobuf
Requires-Dist: numpy >=1.22.0
Requires-Dist: opencv-python
Requires-Dist: scipy
Requires-Dist: matplotlib
